dangasa/__init__.py
dangasa/manager_model.py
dangasa/manager/__init__.py
dangasa/manager/config.py
dangasa/manager/model_manager.py
dangasa/manager/config_files/__init__.py
dangasa/manager/config_files/dangasa_settings.py
dangasa/manager/config_files/generator.py
dangasa/manager/config_files/pagination.py
dangasa/manager/config_files/schema.py
dangasa/manager/config_files/settings.py
dangasa/manager/model_crud_files/ListCreateApiView.py-tpl
dangasa/manager/model_crud_files/RetrieveAPIView.py-tpl
dangasa/manager/model_crud_files/__init__.py
dangasa/manager/model_crud_files/serializers.py-tpl
dangasa/manager/model_crud_files/serializers_class.py-tpl
dangasa/manager/model_crud_files/urls.py-tpl
dangasa/manager/model_crud_files/views.py-tpl
Dangasa-1.0.1.dist-info/LICENSE
Dangasa-1.0.1.dist-info/METADATA
Dangasa-1.0.1.dist-info/WHEEL
Dangasa-1.0.1.dist-info/entry_points.txt
Dangasa-1.0.1.dist-info/top_level.txt
Dangasa-1.0.1.dist-info/RECORD
